xwpandas/__init__.py
xwpandas/core.py
xwpandas/utils.py
xwpandas-0.1.0.dist-info/METADATA
xwpandas-0.1.0.dist-info/RECORD
xwpandas-0.1.0.dist-info/WHEEL
xwpandas-0.1.0.dist-info/top_level.txt
