Metadata-Version: 2.1
Name: xwpandas
Version: 0.1.0
Summary: High performance Excel IO tools for DataFrame
Home-page: https://github.com/Minjejeon/xwpandas
Author: Minje Jeon
Author-email: i@minje.kr
License: BSD 3-clause
Keywords: excel,pandas,DataFrame,xls,xlsx
Platform: UNKNOWN
Classifier: Development Status :: 3 - Alpha
Classifier: License :: OSI Approved :: BSD License
Classifier: Operating System :: MacOS :: MacOS X
Classifier: Operating System :: Microsoft :: Windows
Classifier: Programming Language :: Python :: 3 :: Only
Classifier: Topic :: Office/Business :: Financial :: Spreadsheet
